pyfn
