Metadata-Version: 2.1
Name: pyfn
Version: 1.3.7
Summary: A python module to process data for Frame Semantic Parsing
Home-page: https://gitlab.com/akb89/pyfn
Author: Alexandre Kabbach
Author-email: akb@3azouz.net
License: MIT
Download-URL: https://pypi.org/project/pyfn/#files
Keywords: framenet,xml,frame semantic parsing,preprocessing,coling2018,pipeline,semafor,open-sesame
Platform: any
Classifier: Development Status :: 5 - Production/Stable
Classifier: Environment :: Console
Classifier: Intended Audience :: Developers
Classifier: Intended Audience :: Education
Classifier: Intended Audience :: Science/Research
Classifier: License :: OSI Approved :: MIT License
Classifier: Natural Language :: English
Classifier: Operating System :: OS Independent
Classifier: Programming Language :: Python :: 3.5
Classifier: Programming Language :: Python :: 3.6
Classifier: Programming Language :: Python :: 3.7
Classifier: Topic :: Scientific/Engineering :: Artificial Intelligence
Classifier: Topic :: Software Development :: Libraries :: Python Modules
Classifier: Topic :: Text Processing :: Linguistic
